{
  "country": "US",
  "denomination": "Five Cents",
  "face_value": 1.0,
  "series": [
    {
      "coins": [
        {
          "business_strikes": null,
          "coin_id": "CA-FIVE-1858-RM",
          "common_names": "1858 Silver Five Cents",
          "composition": {
            "copper": 0.075,
            "silver": 0.925
          },
          "diameter_mm": 15.5,
          "identification_keywords": "Victoria, maple leaves, silver",
          "mint": "RM",
          "obverse_description": "Queen Victoria laureate bust left",
          "proof_strikes": null,
          "rarity": "scarce",
          "reverse_description": "Two maple leaves with denomination",
          "source_citation": "Issue #11 research",
          "varieties": [],
          "year": 1858
        },
        {
          "business_strikes": 2582495,
          "coin_id": "CA-FIVE-1921-P",
          "common_names": "1921 Silver Five Cents (Prince)",
          "composition": {
            "copper": 0.2,
            "silver": 0.8
          },
          "diameter_mm": 15.5,
          "distinguishing_features": "Prince of Canadian coins - most melted, <400 survive",
          "identification_keywords": "George V, maple leaves, key date",
          "mint": "P",
          "notes": "Most of mintage melted when nickel 5-cent introduced",
          "obverse_description": "King George V bust left",
          "proof_strikes": null,
          "rarity": "key",
          "reverse_description": "Two maple leaves with denomination",
          "source_citation": "Issue #11 research",
          "varieties": [],
          "weight_grams": 1.16,
          "year": 1921
        }
      ],
      "composition_periods": [
        {
          "alloy": {},
          "alloy_name": "Unknown",
          "date_range": {
            "end": 1921,
            "start": 1858
          }
        }
      ],
      "official_name": "5 Cents Silver",
      "series_id": "ca_5c_silver",
      "series_name": "5 Cents Silver",
      "specifications": {
        "diameter_mm": 15.5,
        "edge": "plain"
      },
      "years": {
        "end": 1921,
        "start": 1858
      }
    },
    {
      "coins": [
        {
          "business_strikes": null,
          "coin_id": "CA-FIVE-2000-P",
          "common_names": "Modern Nickel",
          "composition": {
            "copper": 0.02,
            "nickel": 0.035,
            "steel": 0.945
          },
          "diameter_mm": 21.2,
          "distinguishing_features": "Multi-ply plated steel",
          "identification_keywords": "Elizabeth II, beaver, steel",
          "mint": "P",
          "obverse_description": "Queen Elizabeth II bust right",
          "proof_strikes": null,
          "rarity": "common",
          "reverse_description": "Beaver on rock",
          "source_citation": "Issue #11 research",
          "varieties": [],
          "weight_grams": 3.95,
          "year": 2000
        }
      ],
      "composition_periods": [
        {
          "alloy": {},
          "alloy_name": "Unknown",
          "date_range": {
            "end": 2000,
            "start": 2000
          },
          "weight": {
            "grams": 3.95
          }
        }
      ],
      "official_name": "5 Cents Steel",
      "series_id": "ca_5c_steel",
      "series_name": "5 Cents Steel",
      "specifications": {
        "diameter_mm": 21.2,
        "edge": "plain"
      },
      "years": {
        "end": 2000,
        "start": 2000
      }
    }
  ]
}